{
	"animations": [
		{
			"loop": false,
			"offsets": [
				0,
				0
			],
			"anim": "idle",
			"fps": 24,
			"name": "idle",
			"indices": []
		},
		{
			"offsets": [
				189,
				35
			],
			"indices": [],
			"fps": 24,
			"anim": "singLEFT",
			"loop": false,
			"name": "left"
		},
		{
			"offsets": [
				10,
				-80
			],
			"indices": [],
			"fps": 24,
			"anim": "singDOWN",
			"loop": false,
			"name": "down"
		},
		{
			"offsets": [
				-10,
				151
			],
			"indices": [],
			"fps": 24,
			"anim": "singUP",
			"loop": false,
			"name": "up"
		},
		{
			"offsets": [
				-2,
				80
			],
			"indices": [],
			"fps": 24,
			"anim": "singRIGHT",
			"loop": false,
			"name": "right"
		}
	],
	"vocals_file": "",
	"no_antialiasing": false,
	"image": "characters/joke/sploinkerz/sploinkerz",
	"position": [
		-80,
		200
	],
	"healthicon": "joke/sploinkerz",
	"flip_x": false,
	"healthbar_colors": [
		40,
		255,
		87
	],
	"camera_position": [
		-20,
		40
	],
	"sing_duration": 4,
	"scale": 1,
	"_editor_isPlayer": false
}